{
  "product_id": "341782963",
  "product_url": "https://www.walmart.com/ip/ZOSI-H-265-8CH-CCTV-Security-System-1080P-Wired-Surveillance-Camera-5MP-Lite-DVR-Home-Outdoor-1TB-HDD-80ft-Night-Vision-Remote-Access/341782963?classType=VARIANT&athbdg=L1400&from=/search",
  "product_name": null,
  "reviews": [
    {
      "reviewer_name": "Anonymous",
      "rating": null,
      "title": "must buy security",
      "review_text": "very easy to install ..doesn't require internet.. great picture day and night.. zoom in and around very easy with wireless mouse instead of wired mouse.. recording is very nice .. screen alert for motion.. ive purchased 2 with no problems in 3 years runs smooth no delays",
      "date": "",
      "verified_purchase": false,
      "helpful_count": 0,
      "sentiment": "positive",
      "confidence": 0.9585,
      "score": 0.9792,
      "roberta_label": "positive",
      "method": "roberta",
      "product_id": "341782963",
      "product_url": "https://www.walmart.com/ip/ZOSI-H-265-8CH-CCTV-Security-System-1080P-Wired-Surveillance-Camera-5MP-Lite-DVR-Home-Outdoor-1TB-HDD-80ft-Night-Vision-Remote-Access/341782963?classType=VARIANT&athbdg=L1400&from=/search",
      "product_name": null
    },
    {
      "reviewer_name": "Anonymous",
      "rating": null,
      "title": "Cameras Work Good!",
      "review_text": "Cameras work good. I had old ones removed and installed these new ones by a handy man. Price is good considering a scammer quoted me over $3,000 to install his cameras. He used big words, but I didn't fall for it and bought these. Be careful out there!",
      "date": "",
      "verified_purchase": false,
      "helpful_count": 0,
      "sentiment": "positive",
      "confidence": 0.8549,
      "score": 0.9274,
      "roberta_label": "positive",
      "method": "roberta",
      "product_id": "341782963",
      "product_url": "https://www.walmart.com/ip/ZOSI-H-265-8CH-CCTV-Security-System-1080P-Wired-Surveillance-Camera-5MP-Lite-DVR-Home-Outdoor-1TB-HDD-80ft-Night-Vision-Remote-Access/341782963?classType=VARIANT&athbdg=L1400&from=/search",
      "product_name": null
    },
    {
      "reviewer_name": "Anonymous",
      "rating": null,
      "title": "cameras",
      "review_text": "they Are good cameras they are worth the money I would recommend them",
      "date": "",
      "verified_purchase": false,
      "helpful_count": 0,
      "sentiment": "positive",
      "confidence": 0.949,
      "score": 0.9745,
      "roberta_label": "positive",
      "method": "roberta",
      "product_id": "341782963",
      "product_url": "https://www.walmart.com/ip/ZOSI-H-265-8CH-CCTV-Security-System-1080P-Wired-Surveillance-Camera-5MP-Lite-DVR-Home-Outdoor-1TB-HDD-80ft-Night-Vision-Remote-Access/341782963?classType=VARIANT&athbdg=L1400&from=/search",
      "product_name": null
    },
    {
      "reviewer_name": "Anonymous",
      "rating": null,
      "title": "not totally wireless",
      "review_text": "I wasn't knowledgeable of the wireless cameras the cameras has to be powered by a adapter separately.",
      "date": "",
      "verified_purchase": false,
      "helpful_count": 0,
      "sentiment": "neutral",
      "confidence": 0.7026,
      "score": 0.5,
      "roberta_label": "neutral",
      "method": "roberta",
      "product_id": "341782963",
      "product_url": "https://www.walmart.com/ip/ZOSI-H-265-8CH-CCTV-Security-System-1080P-Wired-Surveillance-Camera-5MP-Lite-DVR-Home-Outdoor-1TB-HDD-80ft-Night-Vision-Remote-Access/341782963?classType=VARIANT&athbdg=L1400&from=/search",
      "product_name": null
    },
    {
      "reviewer_name": "Anonymous",
      "rating": null,
      "title": "",
      "review_text": "picture is not that great, but it's good for the price",
      "date": "",
      "verified_purchase": false,
      "helpful_count": 0,
      "sentiment": "neutral",
      "confidence": 0.4397,
      "score": 0.5,
      "roberta_label": "neutral",
      "method": "roberta",
      "product_id": "341782963",
      "product_url": "https://www.walmart.com/ip/ZOSI-H-265-8CH-CCTV-Security-System-1080P-Wired-Surveillance-Camera-5MP-Lite-DVR-Home-Outdoor-1TB-HDD-80ft-Night-Vision-Remote-Access/341782963?classType=VARIANT&athbdg=L1400&from=/search",
      "product_name": null
    },
    {
      "reviewer_name": "Anonymous",
      "rating": null,
      "title": "",
      "review_text": "Cords are not working properly , i loose image on two cameras.",
      "date": "",
      "verified_purchase": false,
      "helpful_count": 0,
      "sentiment": "negative",
      "confidence": 0.9237,
      "score": 0.0382,
      "roberta_label": "negative",
      "method": "roberta",
      "product_id": "341782963",
      "product_url": "https://www.walmart.com/ip/ZOSI-H-265-8CH-CCTV-Security-System-1080P-Wired-Surveillance-Camera-5MP-Lite-DVR-Home-Outdoor-1TB-HDD-80ft-Night-Vision-Remote-Access/341782963?classType=VARIANT&athbdg=L1400&from=/search",
      "product_name": null
    },
    {
      "reviewer_name": "Anonymous",
      "rating": null,
      "title": "very very very upset",
      "review_text": "it's impossible to get it set up where it records there's nobody to talk to I've left messages I've called about this product I can't set it up you can hook the cameras up and plug them in but you can't get them to record you can't monitor them can nothing I've asked people to call me but nobody will",
      "date": "",
      "verified_purchase": false,
      "helpful_count": 0,
      "sentiment": "negative",
      "confidence": 0.9358,
      "score": 0.0321,
      "roberta_label": "negative",
      "method": "roberta",
      "product_id": "341782963",
      "product_url": "https://www.walmart.com/ip/ZOSI-H-265-8CH-CCTV-Security-System-1080P-Wired-Surveillance-Camera-5MP-Lite-DVR-Home-Outdoor-1TB-HDD-80ft-Night-Vision-Remote-Access/341782963?classType=VARIANT&athbdg=L1400&from=/search",
      "product_name": null
    },
    {
      "reviewer_name": "Anonymous",
      "rating": null,
      "title": "Best to look elsewhere",
      "review_text": "Not user friendly ; Directions on setting up uncomprehensible.",
      "date": "",
      "verified_purchase": false,
      "helpful_count": 0,
      "sentiment": "negative",
      "confidence": 0.8738,
      "score": 0.0631,
      "roberta_label": "negative",
      "method": "roberta",
      "product_id": "341782963",
      "product_url": "https://www.walmart.com/ip/ZOSI-H-265-8CH-CCTV-Security-System-1080P-Wired-Surveillance-Camera-5MP-Lite-DVR-Home-Outdoor-1TB-HDD-80ft-Night-Vision-Remote-Access/341782963?classType=VARIANT&athbdg=L1400&from=/search",
      "product_name": null
    },
    {
      "reviewer_name": "Anonymous",
      "rating": null,
      "title": "",
      "review_text": "i think yall sold me a already used equipment cause my dvr says disk lost! and it won't record anything also the booklet that i seen in videos say that it supposed to have some booklet about the dvr which was missing as well.",
      "date": "",
      "verified_purchase": false,
      "helpful_count": 0,
      "sentiment": "negative",
      "confidence": 0.9114,
      "score": 0.0443,
      "roberta_label": "negative",
      "method": "roberta",
      "product_id": "341782963",
      "product_url": "https://www.walmart.com/ip/ZOSI-H-265-8CH-CCTV-Security-System-1080P-Wired-Surveillance-Camera-5MP-Lite-DVR-Home-Outdoor-1TB-HDD-80ft-Night-Vision-Remote-Access/341782963?classType=VARIANT&athbdg=L1400&from=/search",
      "product_name": null
    },
    {
      "reviewer_name": "Anonymous",
      "rating": null,
      "title": "",
      "review_text": "the cameras dont work had to hook it up to my old systems cameras",
      "date": "",
      "verified_purchase": false,
      "helpful_count": 0,
      "sentiment": "negative",
      "confidence": 0.859,
      "score": 0.0705,
      "roberta_label": "negative",
      "method": "roberta",
      "product_id": "341782963",
      "product_url": "https://www.walmart.com/ip/ZOSI-H-265-8CH-CCTV-Security-System-1080P-Wired-Surveillance-Camera-5MP-Lite-DVR-Home-Outdoor-1TB-HDD-80ft-Night-Vision-Remote-Access/341782963?classType=VARIANT&athbdg=L1400&from=/search",
      "product_name": null
    },
    {
      "reviewer_name": "Anonymous",
      "rating": null,
      "title": "",
      "review_text": "it was easy to set up ..the picture clarity is great",
      "date": "",
      "verified_purchase": false,
      "helpful_count": 0,
      "sentiment": "positive",
      "confidence": 0.9752,
      "score": 0.9876,
      "roberta_label": "positive",
      "method": "roberta",
      "product_id": "341782963",
      "product_url": "https://www.walmart.com/ip/ZOSI-H-265-8CH-CCTV-Security-System-1080P-Wired-Surveillance-Camera-5MP-Lite-DVR-Home-Outdoor-1TB-HDD-80ft-Night-Vision-Remote-Access/341782963?classType=VARIANT&athbdg=L1400&from=/search",
      "product_name": null
    },
    {
      "reviewer_name": "Anonymous",
      "rating": null,
      "title": "No hard drive",
      "review_text": "Ordered with a 1 tb hard drive but came without any hard drive at all",
      "date": "",
      "verified_purchase": false,
      "helpful_count": 0,
      "sentiment": "negative",
      "confidence": 0.513,
      "score": 0.2435,
      "roberta_label": "negative",
      "method": "roberta",
      "product_id": "341782963",
      "product_url": "https://www.walmart.com/ip/ZOSI-H-265-8CH-CCTV-Security-System-1080P-Wired-Surveillance-Camera-5MP-Lite-DVR-Home-Outdoor-1TB-HDD-80ft-Night-Vision-Remote-Access/341782963?classType=VARIANT&athbdg=L1400&from=/search",
      "product_name": null
    },
    {
      "reviewer_name": "Anonymous",
      "rating": null,
      "title": "",
      "review_text": "so far it is easy set up, and great picture. it should come with a maneal on how to set it though.",
      "date": "",
      "verified_purchase": false,
      "helpful_count": 0,
      "sentiment": "positive",
      "confidence": 0.9372,
      "score": 0.9686,
      "roberta_label": "positive",
      "method": "roberta",
      "product_id": "341782963",
      "product_url": "https://www.walmart.com/ip/ZOSI-H-265-8CH-CCTV-Security-System-1080P-Wired-Surveillance-Camera-5MP-Lite-DVR-Home-Outdoor-1TB-HDD-80ft-Night-Vision-Remote-Access/341782963?classType=VARIANT&athbdg=L1400&from=/search",
      "product_name": null
    },
    {
      "reviewer_name": "Anonymous",
      "rating": null,
      "title": "Amazing system!",
      "review_text": "Works amazingly and great visual and audio quality",
      "date": "",
      "verified_purchase": false,
      "helpful_count": 0,
      "sentiment": "positive",
      "confidence": 0.9863,
      "score": 0.9932,
      "roberta_label": "positive",
      "method": "roberta",
      "product_id": "341782963",
      "product_url": "https://www.walmart.com/ip/ZOSI-H-265-8CH-CCTV-Security-System-1080P-Wired-Surveillance-Camera-5MP-Lite-DVR-Home-Outdoor-1TB-HDD-80ft-Night-Vision-Remote-Access/341782963?classType=VARIANT&athbdg=L1400&from=/search",
      "product_name": null
    },
    {
      "reviewer_name": "Anonymous",
      "rating": null,
      "title": "",
      "review_text": "The clarity of the pictures are remarkable. We have a small 24\" television to watch them with. Gives us a sence of extra security being able to see who is at the door day or night.",
      "date": "",
      "verified_purchase": false,
      "helpful_count": 0,
      "sentiment": "positive",
      "confidence": 0.859,
      "score": 0.9295,
      "roberta_label": "positive",
      "method": "roberta",
      "product_id": "341782963",
      "product_url": "https://www.walmart.com/ip/ZOSI-H-265-8CH-CCTV-Security-System-1080P-Wired-Surveillance-Camera-5MP-Lite-DVR-Home-Outdoor-1TB-HDD-80ft-Night-Vision-Remote-Access/341782963?classType=VARIANT&athbdg=L1400&from=/search",
      "product_name": null
    },
    {
      "reviewer_name": "Anonymous",
      "rating": null,
      "title": "",
      "review_text": "I would've liked to have them pan back-and-forth but they do not",
      "date": "",
      "verified_purchase": false,
      "helpful_count": 0,
      "sentiment": "neutral",
      "confidence": 0.5592,
      "score": 0.5,
      "roberta_label": "neutral",
      "method": "roberta",
      "product_id": "341782963",
      "product_url": "https://www.walmart.com/ip/ZOSI-H-265-8CH-CCTV-Security-System-1080P-Wired-Surveillance-Camera-5MP-Lite-DVR-Home-Outdoor-1TB-HDD-80ft-Night-Vision-Remote-Access/341782963?classType=VARIANT&athbdg=L1400&from=/search",
      "product_name": null
    },
    {
      "reviewer_name": "Anonymous",
      "rating": null,
      "title": "Not bad for a wired system.",
      "review_text": "Never hooked it up but the plugs are not water proof. So would not work the way I wanted it to.",
      "date": "",
      "verified_purchase": false,
      "helpful_count": 0,
      "sentiment": "negative",
      "confidence": 0.7897,
      "score": 0.1051,
      "roberta_label": "negative",
      "method": "roberta",
      "product_id": "341782963",
      "product_url": "https://www.walmart.com/ip/ZOSI-H-265-8CH-CCTV-Security-System-1080P-Wired-Surveillance-Camera-5MP-Lite-DVR-Home-Outdoor-1TB-HDD-80ft-Night-Vision-Remote-Access/341782963?classType=VARIANT&athbdg=L1400&from=/search",
      "product_name": null
    },
    {
      "reviewer_name": "Anonymous",
      "rating": null,
      "title": "",
      "review_text": "I bought 2 of this cameras. None came with hard drive like it stated in the description. Really upset",
      "date": "",
      "verified_purchase": false,
      "helpful_count": 0,
      "sentiment": "negative",
      "confidence": 0.9022,
      "score": 0.0489,
      "roberta_label": "negative",
      "method": "roberta",
      "product_id": "341782963",
      "product_url": "https://www.walmart.com/ip/ZOSI-H-265-8CH-CCTV-Security-System-1080P-Wired-Surveillance-Camera-5MP-Lite-DVR-Home-Outdoor-1TB-HDD-80ft-Night-Vision-Remote-Access/341782963?classType=VARIANT&athbdg=L1400&from=/search",
      "product_name": null
    },
    {
      "reviewer_name": "Anonymous",
      "rating": null,
      "title": "a good camera system",
      "review_text": "bought this for my son he says its an awesome system for the price good picture ,color, zoom, night vision, etc",
      "date": "",
      "verified_purchase": false,
      "helpful_count": 0,
      "sentiment": "positive",
      "confidence": 0.9811,
      "score": 0.9906,
      "roberta_label": "positive",
      "method": "roberta",
      "product_id": "341782963",
      "product_url": "https://www.walmart.com/ip/ZOSI-H-265-8CH-CCTV-Security-System-1080P-Wired-Surveillance-Camera-5MP-Lite-DVR-Home-Outdoor-1TB-HDD-80ft-Night-Vision-Remote-Access/341782963?classType=VARIANT&athbdg=L1400&from=/search",
      "product_name": null
    }
  ],
  "scraped_at": "2025-10-22T10:27:02.125690"
}