{
  "product_id": "1566385694",
  "product_url": "https://www.walmart.com/ip/SPIEZ-Men-s-Slip-Resistant-Shoes-Waterproof-Oilproof-Lightweight-Non-Slip-Sneakers-Chef-Restaurant-Work-Shoes-Black-Size-9/1566385694?classType=VARIANT&athbdg=L1600&adsRedirect=true",
  "product_name": null,
  "reviews": [
    {
      "reviewer_name": "Anonymous",
      "rating": null,
      "title": "",
      "review_text": "it's a tight shoe for a narrow foot very tight across the top. the link seems to be accurate but the overall shoe itself is tight across the top around the toe area",
      "date": "",
      "verified_purchase": false,
      "helpful_count": 0,
      "sentiment": "neutral",
      "confidence": 0.6506,
      "score": 0.5,
      "roberta_label": "neutral",
      "method": "roberta",
      "product_id": "1566385694",
      "product_url": "https://www.walmart.com/ip/SPIEZ-Men-s-Slip-Resistant-Shoes-Waterproof-Oilproof-Lightweight-Non-Slip-Sneakers-Chef-Restaurant-Work-Shoes-Black-Size-9/1566385694?classType=VARIANT&athbdg=L1600&adsRedirect=true",
      "product_name": null
    },
    {
      "reviewer_name": "Anonymous",
      "rating": null,
      "title": "",
      "review_text": "the neighbor kid starts at Burger King he didn't have their shoes. now he has shoes.tjano you .",
      "date": "",
      "verified_purchase": false,
      "helpful_count": 0,
      "sentiment": "neutral",
      "confidence": 0.597,
      "score": 0.5,
      "roberta_label": "neutral",
      "method": "roberta",
      "product_id": "1566385694",
      "product_url": "https://www.walmart.com/ip/SPIEZ-Men-s-Slip-Resistant-Shoes-Waterproof-Oilproof-Lightweight-Non-Slip-Sneakers-Chef-Restaurant-Work-Shoes-Black-Size-9/1566385694?classType=VARIANT&athbdg=L1600&adsRedirect=true",
      "product_name": null
    },
    {
      "reviewer_name": "Anonymous",
      "rating": null,
      "title": "",
      "review_text": "They seem to attract dust, but well worth the money.",
      "date": "",
      "verified_purchase": false,
      "helpful_count": 0,
      "sentiment": "neutral",
      "confidence": 0.4551,
      "score": 0.5,
      "roberta_label": "neutral",
      "method": "roberta",
      "product_id": "1566385694",
      "product_url": "https://www.walmart.com/ip/SPIEZ-Men-s-Slip-Resistant-Shoes-Waterproof-Oilproof-Lightweight-Non-Slip-Sneakers-Chef-Restaurant-Work-Shoes-Black-Size-9/1566385694?classType=VARIANT&athbdg=L1600&adsRedirect=true",
      "product_name": null
    },
    {
      "reviewer_name": "Anonymous",
      "rating": null,
      "title": "",
      "review_text": "Your shoes are OK for the quality, but they have slip on. It would be better.",
      "date": "",
      "verified_purchase": false,
      "helpful_count": 0,
      "sentiment": "neutral",
      "confidence": 0.4824,
      "score": 0.5,
      "roberta_label": "neutral",
      "method": "roberta",
      "product_id": "1566385694",
      "product_url": "https://www.walmart.com/ip/SPIEZ-Men-s-Slip-Resistant-Shoes-Waterproof-Oilproof-Lightweight-Non-Slip-Sneakers-Chef-Restaurant-Work-Shoes-Black-Size-9/1566385694?classType=VARIANT&athbdg=L1600&adsRedirect=true",
      "product_name": null
    },
    {
      "reviewer_name": "Anonymous",
      "rating": null,
      "title": "",
      "review_text": "My son needed non slip shoes for work and water resistant too these are both",
      "date": "",
      "verified_purchase": false,
      "helpful_count": 0,
      "sentiment": "neutral",
      "confidence": 0.4897,
      "score": 0.5,
      "roberta_label": "neutral",
      "method": "roberta",
      "product_id": "1566385694",
      "product_url": "https://www.walmart.com/ip/SPIEZ-Men-s-Slip-Resistant-Shoes-Waterproof-Oilproof-Lightweight-Non-Slip-Sneakers-Chef-Restaurant-Work-Shoes-Black-Size-9/1566385694?classType=VARIANT&athbdg=L1600&adsRedirect=true",
      "product_name": null
    },
    {
      "reviewer_name": "Anonymous",
      "rating": null,
      "title": "",
      "review_text": "They were to small I put size 13 but they were too small so I give them to my sister",
      "date": "",
      "verified_purchase": false,
      "helpful_count": 0,
      "sentiment": "neutral",
      "confidence": 0.4838,
      "score": 0.5,
      "roberta_label": "neutral",
      "method": "roberta",
      "product_id": "1566385694",
      "product_url": "https://www.walmart.com/ip/SPIEZ-Men-s-Slip-Resistant-Shoes-Waterproof-Oilproof-Lightweight-Non-Slip-Sneakers-Chef-Restaurant-Work-Shoes-Black-Size-9/1566385694?classType=VARIANT&athbdg=L1600&adsRedirect=true",
      "product_name": null
    },
    {
      "reviewer_name": "Anonymous",
      "rating": null,
      "title": "Ehh",
      "review_text": "Very tight on the sides of the shoe.. bottom gets slick with hair/fur or any dust. Overall will do the trick for $30",
      "date": "",
      "verified_purchase": false,
      "helpful_count": 0,
      "sentiment": "neutral",
      "confidence": 0.6454,
      "score": 0.5,
      "roberta_label": "neutral",
      "method": "roberta",
      "product_id": "1566385694",
      "product_url": "https://www.walmart.com/ip/SPIEZ-Men-s-Slip-Resistant-Shoes-Waterproof-Oilproof-Lightweight-Non-Slip-Sneakers-Chef-Restaurant-Work-Shoes-Black-Size-9/1566385694?classType=VARIANT&athbdg=L1600&adsRedirect=true",
      "product_name": null
    },
    {
      "reviewer_name": "Anonymous",
      "rating": null,
      "title": "",
      "review_text": "Considering I could of sworn I ordered Sketchers %26 received Spiez which to me are a notch above the cheapest sneaker Dollar General or Family Dollar has to offer.",
      "date": "",
      "verified_purchase": false,
      "helpful_count": 0,
      "sentiment": "neutral",
      "confidence": 0.5593,
      "score": 0.5,
      "roberta_label": "neutral",
      "method": "roberta",
      "product_id": "1566385694",
      "product_url": "https://www.walmart.com/ip/SPIEZ-Men-s-Slip-Resistant-Shoes-Waterproof-Oilproof-Lightweight-Non-Slip-Sneakers-Chef-Restaurant-Work-Shoes-Black-Size-9/1566385694?classType=VARIANT&athbdg=L1600&adsRedirect=true",
      "product_name": null
    },
    {
      "reviewer_name": "Anonymous",
      "rating": null,
      "title": "Comfy cheap shoe",
      "review_text": "You get what you pay for and 30$ is about what they are worth",
      "date": "",
      "verified_purchase": false,
      "helpful_count": 0,
      "sentiment": "neutral",
      "confidence": 0.502,
      "score": 0.5,
      "roberta_label": "neutral",
      "method": "roberta",
      "product_id": "1566385694",
      "product_url": "https://www.walmart.com/ip/SPIEZ-Men-s-Slip-Resistant-Shoes-Waterproof-Oilproof-Lightweight-Non-Slip-Sneakers-Chef-Restaurant-Work-Shoes-Black-Size-9/1566385694?classType=VARIANT&athbdg=L1600&adsRedirect=true",
      "product_name": null
    },
    {
      "reviewer_name": "Anonymous",
      "rating": null,
      "title": "",
      "review_text": "Never received the item",
      "date": "",
      "verified_purchase": false,
      "helpful_count": 0,
      "sentiment": "neutral",
      "confidence": 0.4911,
      "score": 0.5,
      "roberta_label": "neutral",
      "method": "roberta",
      "product_id": "1566385694",
      "product_url": "https://www.walmart.com/ip/SPIEZ-Men-s-Slip-Resistant-Shoes-Waterproof-Oilproof-Lightweight-Non-Slip-Sneakers-Chef-Restaurant-Work-Shoes-Black-Size-9/1566385694?classType=VARIANT&athbdg=L1600&adsRedirect=true",
      "product_name": null
    },
    {
      "reviewer_name": "Anonymous",
      "rating": null,
      "title": "So-So",
      "review_text": "they do keep your feet dry better than regular shoes but they're not long-lasting they lose support very quickly..",
      "date": "",
      "verified_purchase": false,
      "helpful_count": 0,
      "sentiment": "neutral",
      "confidence": 0.5093,
      "score": 0.5,
      "roberta_label": "neutral",
      "method": "roberta",
      "product_id": "1566385694",
      "product_url": "https://www.walmart.com/ip/SPIEZ-Men-s-Slip-Resistant-Shoes-Waterproof-Oilproof-Lightweight-Non-Slip-Sneakers-Chef-Restaurant-Work-Shoes-Black-Size-9/1566385694?classType=VARIANT&athbdg=L1600&adsRedirect=true",
      "product_name": null
    },
    {
      "reviewer_name": "Anonymous",
      "rating": null,
      "title": "",
      "review_text": "It runs small especially across the top of your foot make sure you tie your shoestring loose because it runs small",
      "date": "",
      "verified_purchase": false,
      "helpful_count": 0,
      "sentiment": "neutral",
      "confidence": 0.6529,
      "score": 0.5,
      "roberta_label": "neutral",
      "method": "roberta",
      "product_id": "1566385694",
      "product_url": "https://www.walmart.com/ip/SPIEZ-Men-s-Slip-Resistant-Shoes-Waterproof-Oilproof-Lightweight-Non-Slip-Sneakers-Chef-Restaurant-Work-Shoes-Black-Size-9/1566385694?classType=VARIANT&athbdg=L1600&adsRedirect=true",
      "product_name": null
    },
    {
      "reviewer_name": "Anonymous",
      "rating": null,
      "title": "cam deliver things on wednesday.",
      "review_text": "if you feliver ot on thursday. I can keep it.",
      "date": "",
      "verified_purchase": false,
      "helpful_count": 0,
      "sentiment": "neutral",
      "confidence": 0.8731,
      "score": 0.5,
      "roberta_label": "neutral",
      "method": "roberta",
      "product_id": "1566385694",
      "product_url": "https://www.walmart.com/ip/SPIEZ-Men-s-Slip-Resistant-Shoes-Waterproof-Oilproof-Lightweight-Non-Slip-Sneakers-Chef-Restaurant-Work-Shoes-Black-Size-9/1566385694?classType=VARIANT&athbdg=L1600&adsRedirect=true",
      "product_name": null
    }
  ],
  "filter": "NEUTRAL_ONLY",
  "scraped_at": "2025-10-24T14:10:13.854210"
}