{
  "product_id": "5779407163",
  "product_url": "https://www.walmart.com/ip/BalanceFrom-Compact-550-LB-Dumbbells-Set-10-Count/5779407163?classType=BUNDLE&adsRedirect=true",
  "product_name": null,
  "reviews": [
    {
      "reviewer_name": "Anonymous",
      "rating": null,
      "title": "They smell, but not forever",
      "review_text": "Agree with other reviews that they have a smell that lasts way longer than it should, even after cleaning them thoroughly. That being said, the price cant be beat for what you get. Also I can say I've had them approximately 4 months and the smell has dissapated.",
      "date": "",
      "verified_purchase": false,
      "helpful_count": 0,
      "sentiment": "neutral",
      "confidence": 0.413,
      "score": 0.5,
      "roberta_label": "neutral",
      "method": "roberta",
      "product_id": "5779407163",
      "product_url": "https://www.walmart.com/ip/BalanceFrom-Compact-550-LB-Dumbbells-Set-10-Count/5779407163?classType=BUNDLE&adsRedirect=true",
      "product_name": null
    },
    {
      "reviewer_name": "Anonymous",
      "rating": null,
      "title": "no stand",
      "review_text": "this is not a 5 because you can get each pair for $20 totalling $80 and I thought the extra cost was because it comes with a stand but it doesn't; the picture just looks like that so maybe it's better to get each set separately. i do like the quality and look so I do recommend this product for that",
      "date": "",
      "verified_purchase": false,
      "helpful_count": 0,
      "sentiment": "neutral",
      "confidence": 0.5986,
      "score": 0.5,
      "roberta_label": "neutral",
      "method": "roberta",
      "product_id": "5779407163",
      "product_url": "https://www.walmart.com/ip/BalanceFrom-Compact-550-LB-Dumbbells-Set-10-Count/5779407163?classType=BUNDLE&adsRedirect=true",
      "product_name": null
    },
    {
      "reviewer_name": "Anonymous",
      "rating": null,
      "title": "Not perfect - Good for price",
      "review_text": "Dissent for the price. If you are looking for perfection, cleanliness, and attention to detail; this is not the product for you. Overall: Good for the price. You need to give some care with caution and love before using them. All of them came as the picture shows.",
      "date": "",
      "verified_purchase": false,
      "helpful_count": 0,
      "sentiment": "neutral",
      "confidence": 0.4343,
      "score": 0.5,
      "roberta_label": "neutral",
      "method": "roberta",
      "product_id": "5779407163",
      "product_url": "https://www.walmart.com/ip/BalanceFrom-Compact-550-LB-Dumbbells-Set-10-Count/5779407163?classType=BUNDLE&adsRedirect=true",
      "product_name": null
    },
    {
      "reviewer_name": "Anonymous",
      "rating": null,
      "title": "Good weights but missing some",
      "review_text": "The weights seem good but we didn't receive the 20 lbs one.",
      "date": "",
      "verified_purchase": false,
      "helpful_count": 0,
      "sentiment": "neutral",
      "confidence": 0.5729,
      "score": 0.5,
      "roberta_label": "neutral",
      "method": "roberta",
      "product_id": "5779407163",
      "product_url": "https://www.walmart.com/ip/BalanceFrom-Compact-550-LB-Dumbbells-Set-10-Count/5779407163?classType=BUNDLE&adsRedirect=true",
      "product_name": null
    },
    {
      "reviewer_name": "Anonymous",
      "rating": null,
      "title": "",
      "review_text": "Less expensive than buying qn equivalent product used.",
      "date": "",
      "verified_purchase": false,
      "helpful_count": 0,
      "sentiment": "neutral",
      "confidence": 0.7161,
      "score": 0.5,
      "roberta_label": "neutral",
      "method": "roberta",
      "product_id": "5779407163",
      "product_url": "https://www.walmart.com/ip/BalanceFrom-Compact-550-LB-Dumbbells-Set-10-Count/5779407163?classType=BUNDLE&adsRedirect=true",
      "product_name": null
    },
    {
      "reviewer_name": "Anonymous",
      "rating": null,
      "title": "Weights are fine/missing rack",
      "review_text": "Weights are fine. Did not come with the rack that was suppose to come with the deal. Would rate higher otherwise.",
      "date": "",
      "verified_purchase": false,
      "helpful_count": 0,
      "sentiment": "neutral",
      "confidence": 0.6206,
      "score": 0.5,
      "roberta_label": "neutral",
      "method": "roberta",
      "product_id": "5779407163",
      "product_url": "https://www.walmart.com/ip/BalanceFrom-Compact-550-LB-Dumbbells-Set-10-Count/5779407163?classType=BUNDLE&adsRedirect=true",
      "product_name": null
    },
    {
      "reviewer_name": "Anonymous",
      "rating": null,
      "title": "Back in shape.",
      "review_text": "It took a lot longer than they originally said to get this item. The box was tore up pretty bad. This is a gift for a convalescing disabled veteran. He will get good use out of it I'm sure.",
      "date": "",
      "verified_purchase": false,
      "helpful_count": 0,
      "sentiment": "neutral",
      "confidence": 0.3929,
      "score": 0.5,
      "roberta_label": "neutral",
      "method": "roberta",
      "product_id": "5779407163",
      "product_url": "https://www.walmart.com/ip/BalanceFrom-Compact-550-LB-Dumbbells-Set-10-Count/5779407163?classType=BUNDLE&adsRedirect=true",
      "product_name": null
    },
    {
      "reviewer_name": "Anonymous",
      "rating": null,
      "title": "",
      "review_text": "Came with four packaging and was missing some weights",
      "date": "",
      "verified_purchase": false,
      "helpful_count": 0,
      "sentiment": "neutral",
      "confidence": 0.5698,
      "score": 0.5,
      "roberta_label": "neutral",
      "method": "roberta",
      "product_id": "5779407163",
      "product_url": "https://www.walmart.com/ip/BalanceFrom-Compact-550-LB-Dumbbells-Set-10-Count/5779407163?classType=BUNDLE&adsRedirect=true",
      "product_name": null
    },
    {
      "reviewer_name": "Anonymous",
      "rating": null,
      "title": "They're dumbbells",
      "review_text": "They're dumbbells, what else is there to say",
      "date": "",
      "verified_purchase": false,
      "helpful_count": 0,
      "sentiment": "neutral",
      "confidence": 0.6048,
      "score": 0.5,
      "roberta_label": "neutral",
      "method": "roberta",
      "product_id": "5779407163",
      "product_url": "https://www.walmart.com/ip/BalanceFrom-Compact-550-LB-Dumbbells-Set-10-Count/5779407163?classType=BUNDLE&adsRedirect=true",
      "product_name": null
    },
    {
      "reviewer_name": "Anonymous",
      "rating": null,
      "title": "",
      "review_text": "I purchased a **** set and got two products stitched together.",
      "date": "",
      "verified_purchase": false,
      "helpful_count": 0,
      "sentiment": "neutral",
      "confidence": 0.8971,
      "score": 0.5,
      "roberta_label": "neutral",
      "method": "roberta",
      "product_id": "5779407163",
      "product_url": "https://www.walmart.com/ip/BalanceFrom-Compact-550-LB-Dumbbells-Set-10-Count/5779407163?classType=BUNDLE&adsRedirect=true",
      "product_name": null
    },
    {
      "reviewer_name": "Anonymous",
      "rating": null,
      "title": "",
      "review_text": "Advertised as having a rack then changed after shipping I",
      "date": "",
      "verified_purchase": false,
      "helpful_count": 0,
      "sentiment": "neutral",
      "confidence": 0.9173,
      "score": 0.5,
      "roberta_label": "neutral",
      "method": "roberta",
      "product_id": "5779407163",
      "product_url": "https://www.walmart.com/ip/BalanceFrom-Compact-550-LB-Dumbbells-Set-10-Count/5779407163?classType=BUNDLE&adsRedirect=true",
      "product_name": null
    },
    {
      "reviewer_name": "Anonymous",
      "rating": null,
      "title": "",
      "review_text": "The dumbbells are in good condition, the problem was how they delivered them, they should pay more attention to that!",
      "date": "",
      "verified_purchase": false,
      "helpful_count": 0,
      "sentiment": "neutral",
      "confidence": 0.4731,
      "score": 0.5,
      "roberta_label": "neutral",
      "method": "roberta",
      "product_id": "5779407163",
      "product_url": "https://www.walmart.com/ip/BalanceFrom-Compact-550-LB-Dumbbells-Set-10-Count/5779407163?classType=BUNDLE&adsRedirect=true",
      "product_name": null
    }
  ],
  "filter": "NEUTRAL_ONLY",
  "scraped_at": "2025-10-24T15:33:54.717114"
}